captcha/__init__.py
captcha/generator.py
captcha/tests.py
captcha/fonts/AuxinMedium.otf
captcha/fonts/MicroSoftYaHei.ttf
captcha/fonts/MicroSoftYaHeiBold.ttf
captcha/fonts/RexBoldInline.otf
captcha/fonts/TruenoBdOlIt.otf
captcha/fonts/__init__.py
easy_captcha-1.3.3.dist-info/LICENSE
easy_captcha-1.3.3.dist-info/METADATA
easy_captcha-1.3.3.dist-info/WHEEL
easy_captcha-1.3.3.dist-info/top_level.txt
easy_captcha-1.3.3.dist-info/RECORD
