Metadata-Version: 2.1
Name: easy-captcha
Version: 1.3.3
Summary: a very easy to use captcha image generator.
Home-page: https://github.com/youngershen/easy-captcha
Author: Younger Shen
Author-email: younger.shen@hotmail.com
License: MIT
Keywords: captcha,image
Platform: UNKNOWN
Classifier: Development Status :: 5 - Production/Stable
Classifier: Intended Audience :: Developers
Classifier: License :: OSI Approved :: MIT License
Classifier: Programming Language :: Python :: 3.6
Classifier: Programming Language :: Python :: 3.7
Classifier: License :: OSI Approved :: MIT License
Classifier: Topic :: Software Development :: Libraries :: Python Modules
Requires-Python: >=3.6
Requires-Dist: pillow
